MANIFEST.in
README.md
setup.cfg
setup.py
mwget/__init__.py
mwget/multiwget.py
mwget/test.py
mwget/util.py
mwget.egg-info/PKG-INFO
mwget.egg-info/SOURCES.txt
mwget.egg-info/dependency_links.txt
mwget.egg-info/top_level.txt