Metadata-Version: 1.1
Name: mwget
Version: 1.5.2
Summary: support threading download file
Home-page: https://github.com/rfyiamcool/mwget
Author: ruifengyun
Author-email: rfyiamcool@163.com
License: MIT
Keywords: wget threading and support break
Platform: UNKNOWN
Classifier: Development Status :: 3 - Alpha
Classifier: Topic :: Internet :: WWW/HTTP
Classifier: License :: OSI Approved :: MIT License
